rainflow.py
rainflow-3.1.1.dist-info/LICENSE.txt
rainflow-3.1.1.dist-info/WHEEL
rainflow-3.1.1.dist-info/METADATA
rainflow-3.1.1.dist-info/RECORD
